imgmisc/__init__.py
imgmisc/imgmisc.py
imgmisc-0.2.2.dist-info/AUTHORS.rst
imgmisc-0.2.2.dist-info/LICENSE
imgmisc-0.2.2.dist-info/METADATA
imgmisc-0.2.2.dist-info/WHEEL
imgmisc-0.2.2.dist-info/top_level.txt
imgmisc-0.2.2.dist-info/RECORD
