Metadata-Version: 2.1
Name: imgmisc
Version: 0.2.2
Summary: imgmisc
Home-page: https://github.com/supersubscript/imgmisc
Author: Henrik Åhl
Author-email: hpa22@cam.ac.uk
License: GNU General Public License v3
Keywords: imgmisc
Classifier: Development Status :: 2 - Pre-Alpha
Classifier: Intended Audience :: Developers
Classifier: License :: OSI Approved :: GNU General Public License v3 (GPLv3)
Classifier: Natural Language :: English
Classifier: Programming Language :: Python :: 3
Classifier: Programming Language :: Python :: 3.5
Classifier: Programming Language :: Python :: 3.6
Classifier: Programming Language :: Python :: 3.7
Classifier: Programming Language :: Python :: 3.8
Requires-Python: !=3.0.*, !=3.1.*, !=3.2.*, !=3.3.*, !=3.4.*
License-File: LICENSE
License-File: AUTHORS.rst
Requires-Dist: Click (>=7.0)
